nion/ui/Application.py
nion/ui/Bitmap.py
nion/ui/CanvasItem.py
nion/ui/Declarative.py
nion/ui/Dialog.py
nion/ui/DrawingContext.py
nion/ui/GridCanvasItem.py
nion/ui/GridFlowCanvasItem.py
nion/ui/ListCanvasItem.py
nion/ui/MouseTrackingCanvasItem.py
nion/ui/PreferencesDialog.py
nion/ui/PyQtProxy.py
nion/ui/QtUserInterface.py
nion/ui/TestUI.py
nion/ui/TreeCanvasItem.py
nion/ui/UserInterface.py
nion/ui/Widgets.py
nion/ui/Window.py
nion/ui/__init__.py
nion/ui/command.py
nion/ui/py.typed
nion/ui/resources/stylesheet.qss
nion/ui/test/CanvasItem_test.py
nion/ui/test/Declarative_test.py
nion/ui/test/Dialog_test.py
nion/ui/test/DrawingContext_test.py
nion/ui/test/GridCanvasItem_test.py
nion/ui/test/ListCanvasItem_test.py
nion/ui/test/TestUI_test.py
nion/ui/test/Widgets_test.py
nion/ui/test/__init__.py
nionui/__init__.py
nionui/__main__.py
nionui-10.2.2.dist-info/licenses/LICENSE.txt
nionui_app/nionui_examples/hello_world/__init__.py
nionui_app/nionui_examples/hello_world/main.py
nionui_app/nionui_examples/ui_demo/Bindings.py
nionui_app/nionui_examples/ui_demo/Buttons.py
nionui_app/nionui_examples/ui_demo/CheckBoxes.py
nionui_app/nionui_examples/ui_demo/ComboBoxes.py
nionui_app/nionui_examples/ui_demo/ComponentContent.py
nionui_app/nionui_examples/ui_demo/ComponentLayout.py
nionui_app/nionui_examples/ui_demo/ComponentPolymorphic.py
nionui_app/nionui_examples/ui_demo/ComponentStack.py
nionui_app/nionui_examples/ui_demo/Compositions.py
nionui_app/nionui_examples/ui_demo/Converters.py
nionui_app/nionui_examples/ui_demo/Groups.py
nionui_app/nionui_examples/ui_demo/LineEdits.py
nionui_app/nionui_examples/ui_demo/ProgressBars.py
nionui_app/nionui_examples/ui_demo/RadioButtons.py
nionui_app/nionui_examples/ui_demo/Sections.py
nionui_app/nionui_examples/ui_demo/Sliders.py
nionui_app/nionui_examples/ui_demo/Stacks.py
nionui_app/nionui_examples/ui_demo/StatusBar.py
nionui_app/nionui_examples/ui_demo/Tabs.py
nionui_app/nionui_examples/ui_demo/__init__.py
nionui_app/nionui_examples/ui_demo/main.py
nionui_app/none/__init__.py
nionui-10.2.2.dist-info/METADATA
nionui-10.2.2.dist-info/WHEEL
nionui-10.2.2.dist-info/entry_points.txt
nionui-10.2.2.dist-info/top_level.txt
nionui-10.2.2.dist-info/RECORD
