Metadata-Version: 2.4
Name: nionui
Version: 10.2.2
Summary: Nion UI framework.
Home-page: https://github.com/nion-software/nionui
Author: Nion Software
Author-email: swift@nion.com
License: Apache-2.0
Classifier: Development Status :: 5 - Production/Stable
Classifier: License :: OSI Approved :: Apache Software License
Classifier: Programming Language :: Python :: 3.11
Classifier: Programming Language :: Python :: 3.12
Classifier: Programming Language :: Python :: 3.13
Requires-Python: >=3.11
License-File: LICENSE.txt
Requires-Dist: imageio>=2.19.0
Requires-Dist: nionutils<5.0.0,>=4.14.0
Requires-Dist: numpy<3.0,>=2.0
Dynamic: license-file
